pytest_iovis/__init__.py
pytest_iovis/_file.py
pytest_iovis/_fixtures.py
pytest_iovis/_types.py
pytest_iovis/_utils.py
pytest_iovis/_venv_builder.py
pytest_iovis/plugin.py
pytest_iovis/py.typed
pytest_iovis/_subplugins/__init__.py
pytest_iovis/_subplugins/discovery.py
pytest_iovis/_subplugins/markup.py
pytest_iovis/_subplugins/papermill_runner.py
pytest_iovis-0.1.0.dist-info/LICENSE
pytest_iovis-0.1.0.dist-info/METADATA
pytest_iovis-0.1.0.dist-info/WHEEL
pytest_iovis-0.1.0.dist-info/entry_points.txt
pytest_iovis-0.1.0.dist-info/top_level.txt
pytest_iovis-0.1.0.dist-info/RECORD
