Metadata-Version: 2.1
Name: pytest-iovis
Version: 0.1.0
Summary: A Pytest plugin to enable Jupyter Notebook testing with Papermill
Project-URL: Source, https://github.com/kdestin/pytest-iovis
Classifier: Development Status :: 4 - Beta
Classifier: Framework :: Pytest
Classifier: Intended Audience :: Developers
Classifier: Topic :: Software Development :: Testing
Classifier: Programming Language :: Python
Classifier: Programming Language :: Python :: 3
Classifier: Programming Language :: Python :: 3.9
Classifier: Programming Language :: Python :: 3.10
Classifier: Programming Language :: Python :: 3.11
Classifier: Programming Language :: Python :: 3.12
Classifier: Programming Language :: Python :: 3.13
Classifier: Programming Language :: Python :: 3 :: Only
Classifier: Programming Language :: Python :: Implementation :: CPython
Classifier: Programming Language :: Python :: Implementation :: PyPy
Classifier: Operating System :: OS Independent
Classifier: License :: OSI Approved :: MIT License
Requires-Python: >=3.9
License-File: LICENSE
Requires-Dist: pytest >=7.1.0
Requires-Dist: typing-extensions >=4.0
Provides-Extra: dev
Requires-Dist: tox ~=4.0 ; extra == 'dev'
Requires-Dist: pre-commit ; extra == 'dev'
Requires-Dist: mypy ~=1.0 ; extra == 'dev'
Requires-Dist: pytest-iovis[papermill] ; extra == 'dev'
Requires-Dist: ipykernel >=6 ; extra == 'dev'
Provides-Extra: papermill
Requires-Dist: papermill ~=2.0 ; extra == 'papermill'
